<?xml version="1.0" encoding="UTF-8"?>

<!DOCTYPE document PUBLIC "-//APACHE//DTD Documentation V2.0//EN" "http://forrest.apache.org/dtd/document-v20.dtd">
<document>
  <header>
    <title>jManage Roadmap</title>
  </header>
  <body>
      <p>
          This documents provides a high level jManage roadmap.
          This roadmap will change based on the needs of the jManage users.
      </p>
      <p>
        <strong>2.0 release</strong>
        <br/><br/>
          - Dashboards.
        <br/>
          - Non-JMX Application connector framework.
        <br/>
          - Application heartbeat monitor.
        <br/>
          - Database monitoring (Oracle).
        <br/>
         - Historical Graphing. (coming soon) 
        <br/><br/>
      </p>
      <p>
        <strong>3.0 release</strong>
          <br/><br/>
            - Performance management.
          <br/>
            - Root cause analysis.
          <br/>
            - Operating system monitoring.
          <br/>
	        - Application specific knowledge modules.
          <br/>
            - Network interface monitoring.
      </p>
      <p>
           <br/>
           If there are other features that you would like to see in jManage, please
           add them <a href="http://sourceforge.net/tracker/?func=add&amp;group_id=111374&amp;atid=659060">here</a>.
      </p>
  </body>
</document>
